SafeCrypt/__init__.py
SafeCrypt/encryption.py
SafeCrypt/main.py
tests/__init__.py
tests/test_encryption.py
safecrypt-0.1.0.dist-info/LICENSE
safecrypt-0.1.0.dist-info/METADATA
safecrypt-0.1.0.dist-info/WHEEL
safecrypt-0.1.0.dist-info/entry_points.txt
safecrypt-0.1.0.dist-info/top_level.txt
safecrypt-0.1.0.dist-info/RECORD
