Metadata-Version: 2.1
Name: safecrypt
Version: 0.1.0
Summary: file encryption and decryption tool
Home-page: https://github.com/HusseinTahaDEV/SafeCrypt
Author: Hussein taha
Author-email: ceo.husseintaha@gamil.com
Classifier: Development Status :: 3 - Alpha
Classifier: Intended Audience :: Developers
Classifier: License :: OSI Approved :: MIT License
Classifier: Programming Language :: Python :: 3
Classifier: Programming Language :: Python :: 3.7
Classifier: Programming Language :: Python :: 3.8
Classifier: Programming Language :: Python :: 3.9
Classifier: Programming Language :: Python :: 3.10
License-File: LICENSE
Requires-Dist: cryptography
Requires-Dist: PyQt5
